sertool/__init__.py
sertool/__main__.py
sertool/cli.py
sertool/serdev.py
sertool/term.py
sertool-0.0.2.dist-info/LICENSE.txt
sertool-0.0.2.dist-info/METADATA
sertool-0.0.2.dist-info/WHEEL
sertool-0.0.2.dist-info/entry_points.txt
sertool-0.0.2.dist-info/top_level.txt
sertool-0.0.2.dist-info/RECORD
